LICENSE
README.md
setup.py
httprober/__init__.py
httprober/httprober.py
httprober.egg-info/PKG-INFO
httprober.egg-info/SOURCES.txt
httprober.egg-info/dependency_links.txt
httprober.egg-info/entry_points.txt
httprober.egg-info/requires.txt
httprober.egg-info/top_level.txt